anycaptcha/__init__.py
anycaptcha/_transport/__init__.py
anycaptcha/_transport/base.py
anycaptcha/_transport/http_transport.py
anycaptcha/captcha/__init__.py
anycaptcha/captcha/base.py
anycaptcha/captcha/capy.py
anycaptcha/captcha/funcaptcha.py
anycaptcha/captcha/geetest.py
anycaptcha/captcha/geetest_v4.py
anycaptcha/captcha/hcaptcha.py
anycaptcha/captcha/image.py
anycaptcha/captcha/keycaptcha.py
anycaptcha/captcha/recaptcha_v2.py
anycaptcha/captcha/recaptcha_v3.py
anycaptcha/captcha/text.py
anycaptcha/enums.py
anycaptcha/errors.py
anycaptcha/service/__init__.py
anycaptcha/service/anti_captcha.py
anycaptcha/service/azcaptcha.py
anycaptcha/service/base.py
anycaptcha/service/capmonster.py
anycaptcha/service/capsolver.py
anycaptcha/service/captcha_guru.py
anycaptcha/service/cptch_net.py
anycaptcha/service/deathbycaptcha.py
anycaptcha/service/multibot_captcha.py
anycaptcha/service/rucaptcha.py
anycaptcha/service/sctg_captcha.py
anycaptcha/service/twocaptcha.py
anycaptcha/solver.py
anycaptcha-1.5.4.dist-info/LICENSE
anycaptcha-1.5.4.dist-info/METADATA
anycaptcha-1.5.4.dist-info/WHEEL
anycaptcha-1.5.4.dist-info/RECORD
