Metadata-Version: 2.1
Name: anycaptcha
Version: 1.5.4
Summary: All captcha solving services in one lib
Home-page: https://github.com/alenkimov/anycaptcha
Author: Alen
Author-email: alen.kimov@gmail.com
Requires-Python: >=3.11,<4.0
Classifier: Programming Language :: Python :: 3
Classifier: Programming Language :: Python :: 3.11
Classifier: Programming Language :: Python :: 3.12
Requires-Dist: better-proxy (>=1.1)
Requires-Dist: filetype (>=1.2.0,<2.0.0)
Requires-Dist: httpx (>=0.22)
Requires-Dist: pydantic (>=1)
Project-URL: Repository, https://github.com/alenkimov/anycaptcha
